{
    "prefabs": {
        "chamber": {
            "mesh": "./resources/models/chamber.obj",
            "scripts": []
        },
        "pedestal": {
            "mesh": "./resources/models/pedestal.obj",
            "scripts": []
        },
        "railing": {
            "mesh": "./resources/models/railing.obj",
            "scripts": []
        },
        "judge_box": {
            "mesh": "./resources/models/judge_box.obj",
            "scripts": []
        },
        "spikes": {
            "mesh": "./resources/models/spikes.obj",
            "scripts": []
        },
        "light_manager": {
            "scripts": ["LightManager"]
        }
    },
    "camera": {
        "position": [0.07689375, 2.5645797, 6.263313],
        "rotation": [0.073999904, -3.1019998]
    },
    "point_lights": [
        {
            "color": [1.5, 1.5, 2.0],
            "position": [0.0, 1.0, 0.0],
            "halo_intensity": 0.0
        }
    ],
    "spot_lights": [
        {
            "color": [0.5, 0.5, 1.1],
            "position": [0, 1.5, 0],
            "direction": [0, -1, 0],
            "angle_inside": 45.0,
            "angle_outside": 48.0,
            "halo_intensity": 0.2
        }
    ],
    "entities": [
        {
            "prefab": "chamber"
        },
        {
            "prefab": "judge_box"
        },
        {
            "prefab": "spikes"
        },
        {
            "prefab": "pedestal"
        },
        {
            "prefab": "railing"
        }
    ]
}

